oslo_limit/__init__.py
oslo_limit/_i18n.py
oslo_limit/exception.py
oslo_limit/fixture.py
oslo_limit/limit.py
oslo_limit/opts.py
oslo_limit/py.typed
oslo_limit/tests/__init__.py
oslo_limit/tests/test_fixture.py
oslo_limit/tests/test_limit.py
oslo_limit-2.9.2.dist-info/licenses/AUTHORS
oslo_limit-2.9.2.dist-info/licenses/LICENSE
oslo_limit-2.9.2.dist-info/METADATA
oslo_limit-2.9.2.dist-info/WHEEL
oslo_limit-2.9.2.dist-info/entry_points.txt
oslo_limit-2.9.2.dist-info/pbr.json
oslo_limit-2.9.2.dist-info/top_level.txt
oslo_limit-2.9.2.dist-info/RECORD
